yta_mongo/__init__.py
yta_mongo/clients.py
yta_mongo/validation.py
yta_mongo-0.0.4.dist-info/LICENSE
yta_mongo-0.0.4.dist-info/METADATA
yta_mongo-0.0.4.dist-info/WHEEL
yta_mongo-0.0.4.dist-info/RECORD
