Metadata-Version: 2.3
Name: yta-mongo
Version: 0.0.4
Summary: 
Author: danialcala94
Author-email: danielalcalavalera@gmail.com
Requires-Python: ==3.9
Classifier: Programming Language :: Python :: 3
Classifier: Programming Language :: Python :: 3.9
Requires-Dist: pymongo (>=3.11.0,<3.12.0)
Requires-Dist: yta_general_utils (>=0.0.250,<0.1.0)
